letterboxed/__init__.py
letterboxed/__main__.py
letterboxed/dictionary.py
letterboxed/letterbox.py
letterboxed-0.0.6.dist-info/METADATA
letterboxed-0.0.6.dist-info/WHEEL
letterboxed-0.0.6.dist-info/entry_points.txt
letterboxed-0.0.6.dist-info/top_level.txt
letterboxed-0.0.6.dist-info/RECORD
