Metadata-Version: 2.1
Name: letterboxed
Version: 0.0.6
Summary: Solve the daily Letterboxed word puzzle from the New York Times.
Project-URL: Homepage, https://github.com/aaronsegura/letterboxed
Project-URL: Repository, https://github.com/aaronsegura/letterboxed
Project-URL: Issues, https://github.com/aaronsegura/letterboxed/issues
Requires-Dist: requests
